data_class_detection/__init__.py
data_class_detection/client.py
data_class_detection/embed.pkl
data_class_detection/node_map100.pkl
data_class_detection/parser/Java8Lexer.py
data_class_detection/parser/Java8Listener.py
data_class_detection/parser/Java8Parser.py
data_class_detection/parser/__init__.py
data_class_detection/parser/ast.py
data_class_detection/parser/sample.py
data_class_detection-0.0.7.dist-info/LICENSE
data_class_detection-0.0.7.dist-info/METADATA
data_class_detection-0.0.7.dist-info/WHEEL
data_class_detection-0.0.7.dist-info/top_level.txt
data_class_detection-0.0.7.dist-info/RECORD
